[
  {
    "Seleção": "França",
    "1º Grupo": "100.0%",
    "2º Grupo": "0.0%",
    "3º Grupo": "0.0%",
    "4º Grupo": "0.0%",
    "Top 32": "100.0%",
    "Oitavas": "86.7%",
    "Quartas": "64.3%",
    "Semi": "48.8%",
    "Final": "33.4%",
    "Campeão": "22.2%"
  },
  {
    "Seleção": "Argentina",
    "1º Grupo": "100.0%",
    "2º Grupo": "0.0%",
    "3º Grupo": "0.0%",
    "4º Grupo": "0.0%",
    "Top 32": "100.0%",
    "Oitavas": "89.2%",
    "Quartas": "77.1%",
    "Semi": "59.3%",
    "Final": "36.7%",
    "Campeão": "19.9%"
  },
  {
    "Seleção": "Espanha",
    "1º Grupo": "100.0%",
    "2º Grupo": "0.0%",
    "3º Grupo": "0.0%",
    "4º Grupo": "0.0%",
    "Top 32": "100.0%",
    "Oitavas": "81.5%",
    "Quartas": "49.9%",
    "Semi": "35.3%",
    "Final": "18.6%",
    "Campeão": "10.7%"
  },
  {
    "Seleção": "Inglaterra",
    "1º Grupo": "100.0%",
    "2º Grupo": "0.0%",
    "3º Grupo": "0.0%",
    "4º Grupo": "0.0%",
    "Top 32": "100.0%",
    "Oitavas": "80.2%",
    "Quartas": "55.4%",
    "Semi": "34.7%",
    "Final": "20.3%",
    "Campeão": "10.4%"
  },
  {
    "Seleção": "Portugal",
    "1º Grupo": "0.0%",
    "2º Grupo": "100.0%",
    "3º Grupo": "0.0%",
    "4º Grupo": "0.0%",
    "Top 32": "100.0%",
    "Oitavas": "72.2%",
    "Quartas": "36.7%",
    "Semi": "24.2%",
    "Final": "11.6%",
    "Campeão": "6.1%"
  },
  {
    "Seleção": "Brasil",
    "1º Grupo": "100.0%",
    "2º Grupo": "0.0%",
    "3º Grupo": "0.0%",
    "4º Grupo": "0.0%",
    "Top 32": "100.0%",
    "Oitavas": "63.6%",
    "Quartas": "41.6%",
    "Semi": "22.7%",
    "Final": "12.3%",
    "Campeão": "5.7%"
  },
  {
    "Seleção": "Holanda",
    "1º Grupo": "100.0%",
    "2º Grupo": "0.0%",
    "3º Grupo": "0.0%",
    "4º Grupo": "0.0%",
    "Top 32": "100.0%",
    "Oitavas": "61.5%",
    "Quartas": "49.6%",
    "Semi": "20.1%",
    "Final": "10.1%",
    "Campeão": "4.9%"
  },
  {
    "Seleção": "Alemanha",
    "1º Grupo": "100.0%",
    "2º Grupo": "0.0%",
    "3º Grupo": "0.0%",
    "4º Grupo": "0.0%",
    "Top 32": "100.0%",
    "Oitavas": "81.4%",
    "Quartas": "28.9%",
    "Semi": "16.8%",
    "Final": "8.1%",
    "Campeão": "3.8%"
  },
  {
    "Seleção": "Estados Unidos",
    "1º Grupo": "100.0%",
    "2º Grupo": "0.0%",
    "3º Grupo": "0.0%",
    "4º Grupo": "0.0%",
    "Top 32": "100.0%",
    "Oitavas": "70.3%",
    "Quartas": "41.4%",
    "Semi": "16.8%",
    "Final": "6.4%",
    "Campeão": "2.8%"
  },
  {
    "Seleção": "Colômbia",
    "1º Grupo": "100.0%",
    "2º Grupo": "0.0%",
    "3º Grupo": "0.0%",
    "4º Grupo": "0.0%",
    "Top 32": "100.0%",
    "Oitavas": "72.8%",
    "Quartas": "46.4%",
    "Semi": "17.9%",
    "Final": "7.2%",
    "Campeão": "2.4%"
  },
  {
    "Seleção": "Noruega",
    "1º Grupo": "0.0%",
    "2º Grupo": "100.0%",
    "3º Grupo": "0.0%",
    "4º Grupo": "0.0%",
    "Top 32": "100.0%",
    "Oitavas": "66.7%",
    "Quartas": "29.7%",
    "Semi": "13.2%",
    "Final": "5.9%",
    "Campeão": "2.2%"
  },
  {
    "Seleção": "México",
    "1º Grupo": "100.0%",
    "2º Grupo": "0.0%",
    "3º Grupo": "0.0%",
    "4º Grupo": "0.0%",
    "Top 32": "100.0%",
    "Oitavas": "61.2%",
    "Quartas": "25.2%",
    "Semi": "11.9%",
    "Final": "5.3%",
    "Campeão": "1.9%"
  },
  {
    "Seleção": "Bélgica",
    "1º Grupo": "100.0%",
    "2º Grupo": "0.0%",
    "3º Grupo": "0.0%",
    "4º Grupo": "0.0%",
    "Top 32": "100.0%",
    "Oitavas": "59.3%",
    "Quartas": "30.2%",
    "Semi": "10.9%",
    "Final": "3.7%",
    "Campeão": "1.4%"
  },
  {
    "Seleção": "Marrocos",
    "1º Grupo": "0.0%",
    "2º Grupo": "100.0%",
    "3º Grupo": "0.0%",
    "4º Grupo": "0.0%",
    "Top 32": "100.0%",
    "Oitavas": "38.5%",
    "Quartas": "27.9%",
    "Semi": "8.6%",
    "Final": "3.4%",
    "Campeão": "1.3%"
  },
  {
    "Seleção": "Japão",
    "1º Grupo": "0.0%",
    "2º Grupo": "100.0%",
    "3º Grupo": "0.0%",
    "4º Grupo": "0.0%",
    "Top 32": "100.0%",
    "Oitavas": "36.4%",
    "Quartas": "19.0%",
    "Semi": "7.9%",
    "Final": "3.3%",
    "Campeão": "1.1%"
  },
  {
    "Seleção": "Suíça",
    "1º Grupo": "100.0%",
    "2º Grupo": "0.0%",
    "3º Grupo": "0.0%",
    "4º Grupo": "0.0%",
    "Top 32": "100.0%",
    "Oitavas": "68.9%",
    "Quartas": "33.2%",
    "Semi": "10.7%",
    "Final": "3.5%",
    "Campeão": "0.9%"
  },
  {
    "Seleção": "Equador",
    "1º Grupo": "0.0%",
    "2º Grupo": "0.0%",
    "3º Grupo": "100.0%",
    "4º Grupo": "0.0%",
    "Top 32": "100.0%",
    "Oitavas": "38.8%",
    "Quartas": "12.3%",
    "Semi": "4.5%",
    "Final": "1.6%",
    "Campeão": "0.4%"
  },
  {
    "Seleção": "Senegal",
    "1º Grupo": "0.0%",
    "2º Grupo": "0.0%",
    "3º Grupo": "100.0%",
    "4º Grupo": "0.0%",
    "Top 32": "100.0%",
    "Oitavas": "40.7%",
    "Quartas": "17.0%",
    "Semi": "4.8%",
    "Final": "1.3%",
    "Campeão": "0.4%"
  },
  {
    "Seleção": "Croácia",
    "1º Grupo": "0.0%",
    "2º Grupo": "100.0%",
    "3º Grupo": "0.0%",
    "4º Grupo": "0.0%",
    "Top 32": "100.0%",
    "Oitavas": "27.8%",
    "Quartas": "8.3%",
    "Semi": "3.6%",
    "Final": "1.0%",
    "Campeão": "0.3%"
  },
  {
    "Seleção": "Costa do Marfim",
    "1º Grupo": "0.0%",
    "2º Grupo": "100.0%",
    "3º Grupo": "0.0%",
    "4º Grupo": "0.0%",
    "Top 32": "100.0%",
    "Oitavas": "33.3%",
    "Quartas": "9.7%",
    "Semi": "2.9%",
    "Final": "0.9%",
    "Campeão": "0.2%"
  },
  {
    "Seleção": "Canadá",
    "1º Grupo": "0.0%",
    "2º Grupo": "100.0%",
    "3º Grupo": "0.0%",
    "4º Grupo": "0.0%",
    "Top 32": "100.0%",
    "Oitavas": "67.8%",
    "Quartas": "17.8%",
    "Semi": "3.2%",
    "Final": "0.8%",
    "Campeão": "0.2%"
  },
  {
    "Seleção": "Bósnia e Herzegovina",
    "1º Grupo": "0.0%",
    "2º Grupo": "0.0%",
    "3º Grupo": "100.0%",
    "4º Grupo": "0.0%",
    "Top 32": "100.0%",
    "Oitavas": "29.7%",
    "Quartas": "11.3%",
    "Semi": "2.6%",
    "Final": "0.6%",
    "Campeão": "0.1%"
  },
  {
    "Seleção": "RD do Congo",
    "1º Grupo": "0.0%",
    "2º Grupo": "0.0%",
    "3º Grupo": "100.0%",
    "4º Grupo": "0.0%",
    "Top 32": "100.0%",
    "Oitavas": "19.8%",
    "Quartas": "7.1%",
    "Semi": "2.2%",
    "Final": "0.6%",
    "Campeão": "0.1%"
  },
  {
    "Seleção": "Egito",
    "1º Grupo": "0.0%",
    "2º Grupo": "100.0%",
    "3º Grupo": "0.0%",
    "4º Grupo": "0.0%",
    "Top 32": "100.0%",
    "Oitavas": "50.9%",
    "Quartas": "9.4%",
    "Semi": "3.4%",
    "Final": "0.7%",
    "Campeão": "0.1%"
  },
  {
    "Seleção": "Austrália",
    "1º Grupo": "0.0%",
    "2º Grupo": "100.0%",
    "3º Grupo": "0.0%",
    "4º Grupo": "0.0%",
    "Top 32": "100.0%",
    "Oitavas": "49.1%",
    "Quartas": "8.8%",
    "Semi": "3.1%",
    "Final": "0.6%",
    "Campeão": "0.1%"
  },
  {
    "Seleção": "Suécia",
    "1º Grupo": "0.0%",
    "2º Grupo": "0.0%",
    "3º Grupo": "100.0%",
    "4º Grupo": "0.0%",
    "Top 32": "100.0%",
    "Oitavas": "13.3%",
    "Quartas": "4.4%",
    "Semi": "1.6%",
    "Final": "0.4%",
    "Campeão": "0.1%"
  },
  {
    "Seleção": "Áustria",
    "1º Grupo": "0.0%",
    "2º Grupo": "100.0%",
    "3º Grupo": "0.0%",
    "4º Grupo": "0.0%",
    "Top 32": "100.0%",
    "Oitavas": "18.5%",
    "Quartas": "5.1%",
    "Semi": "1.8%",
    "Final": "0.4%",
    "Campeão": "0.1%"
  },
  {
    "Seleção": "Gana",
    "1º Grupo": "0.0%",
    "2º Grupo": "0.0%",
    "3º Grupo": "100.0%",
    "4º Grupo": "0.0%",
    "Top 32": "100.0%",
    "Oitavas": "27.2%",
    "Quartas": "11.0%",
    "Semi": "2.4%",
    "Final": "0.5%",
    "Campeão": "0.1%"
  },
  {
    "Seleção": "Argélia",
    "1º Grupo": "0.0%",
    "2º Grupo": "0.0%",
    "3º Grupo": "100.0%",
    "4º Grupo": "0.0%",
    "Top 32": "100.0%",
    "Oitavas": "31.1%",
    "Quartas": "9.4%",
    "Semi": "1.8%",
    "Final": "0.3%",
    "Campeão": "0.0%"
  },
  {
    "Seleção": "Cabo Verde",
    "1º Grupo": "0.0%",
    "2º Grupo": "100.0%",
    "3º Grupo": "0.0%",
    "4º Grupo": "0.0%",
    "Top 32": "100.0%",
    "Oitavas": "10.8%",
    "Quartas": "4.7%",
    "Semi": "1.4%",
    "Final": "0.2%",
    "Campeão": "0.0%"
  },
  {
    "Seleção": "Paraguai",
    "1º Grupo": "0.0%",
    "2º Grupo": "0.0%",
    "3º Grupo": "100.0%",
    "4º Grupo": "0.0%",
    "Top 32": "100.0%",
    "Oitavas": "18.6%",
    "Quartas": "2.4%",
    "Semi": "0.6%",
    "Final": "0.1%",
    "Campeão": "0.0%"
  },
  {
    "Seleção": "África do Sul",
    "1º Grupo": "0.0%",
    "2º Grupo": "100.0%",
    "3º Grupo": "0.0%",
    "4º Grupo": "0.0%",
    "Top 32": "100.0%",
    "Oitavas": "32.2%",
    "Quartas": "4.7%",
    "Semi": "0.5%",
    "Final": "0.1%",
    "Campeão": "0.0%"
  },
  {
    "Seleção": "Uruguai",
    "1º Grupo": "0.0%",
    "2º Grupo": "0.0%",
    "3º Grupo": "100.0%",
    "4º Grupo": "0.0%",
    "Top 32": "0.0%",
    "Oitavas": "0.0%",
    "Quartas": "0.0%",
    "Semi": "0.0%",
    "Final": "0.0%",
    "Campeão": "0.0%"
  },
  {
    "Seleção": "Irã",
    "1º Grupo": "0.0%",
    "2º Grupo": "0.0%",
    "3º Grupo": "100.0%",
    "4º Grupo": "0.0%",
    "Top 32": "0.0%",
    "Oitavas": "0.0%",
    "Quartas": "0.0%",
    "Semi": "0.0%",
    "Final": "0.0%",
    "Campeão": "0.0%"
  },
  {
    "Seleção": "Turquia",
    "1º Grupo": "0.0%",
    "2º Grupo": "0.0%",
    "3º Grupo": "0.0%",
    "4º Grupo": "100.0%",
    "Top 32": "0.0%",
    "Oitavas": "0.0%",
    "Quartas": "0.0%",
    "Semi": "0.0%",
    "Final": "0.0%",
    "Campeão": "0.0%"
  },
  {
    "Seleção": "Coreia do Sul",
    "1º Grupo": "0.0%",
    "2º Grupo": "0.0%",
    "3º Grupo": "100.0%",
    "4º Grupo": "0.0%",
    "Top 32": "0.0%",
    "Oitavas": "0.0%",
    "Quartas": "0.0%",
    "Semi": "0.0%",
    "Final": "0.0%",
    "Campeão": "0.0%"
  },
  {
    "Seleção": "Panamá",
    "1º Grupo": "0.0%",
    "2º Grupo": "0.0%",
    "3º Grupo": "0.0%",
    "4º Grupo": "100.0%",
    "Top 32": "0.0%",
    "Oitavas": "0.0%",
    "Quartas": "0.0%",
    "Semi": "0.0%",
    "Final": "0.0%",
    "Campeão": "0.0%"
  },
  {
    "Seleção": "Tcheca",
    "1º Grupo": "0.0%",
    "2º Grupo": "0.0%",
    "3º Grupo": "0.0%",
    "4º Grupo": "100.0%",
    "Top 32": "0.0%",
    "Oitavas": "0.0%",
    "Quartas": "0.0%",
    "Semi": "0.0%",
    "Final": "0.0%",
    "Campeão": "0.0%"
  },
  {
    "Seleção": "Escócia",
    "1º Grupo": "0.0%",
    "2º Grupo": "0.0%",
    "3º Grupo": "100.0%",
    "4º Grupo": "0.0%",
    "Top 32": "0.0%",
    "Oitavas": "0.0%",
    "Quartas": "0.0%",
    "Semi": "0.0%",
    "Final": "0.0%",
    "Campeão": "0.0%"
  },
  {
    "Seleção": "Tunísia",
    "1º Grupo": "0.0%",
    "2º Grupo": "0.0%",
    "3º Grupo": "0.0%",
    "4º Grupo": "100.0%",
    "Top 32": "0.0%",
    "Oitavas": "0.0%",
    "Quartas": "0.0%",
    "Semi": "0.0%",
    "Final": "0.0%",
    "Campeão": "0.0%"
  },
  {
    "Seleção": "Uzbequistão",
    "1º Grupo": "0.0%",
    "2º Grupo": "0.0%",
    "3º Grupo": "0.0%",
    "4º Grupo": "100.0%",
    "Top 32": "0.0%",
    "Oitavas": "0.0%",
    "Quartas": "0.0%",
    "Semi": "0.0%",
    "Final": "0.0%",
    "Campeão": "0.0%"
  },
  {
    "Seleção": "Catar",
    "1º Grupo": "0.0%",
    "2º Grupo": "0.0%",
    "3º Grupo": "0.0%",
    "4º Grupo": "100.0%",
    "Top 32": "0.0%",
    "Oitavas": "0.0%",
    "Quartas": "0.0%",
    "Semi": "0.0%",
    "Final": "0.0%",
    "Campeão": "0.0%"
  },
  {
    "Seleção": "Iraque",
    "1º Grupo": "0.0%",
    "2º Grupo": "0.0%",
    "3º Grupo": "0.0%",
    "4º Grupo": "100.0%",
    "Top 32": "0.0%",
    "Oitavas": "0.0%",
    "Quartas": "0.0%",
    "Semi": "0.0%",
    "Final": "0.0%",
    "Campeão": "0.0%"
  },
  {
    "Seleção": "Arábia Saudita",
    "1º Grupo": "0.0%",
    "2º Grupo": "0.0%",
    "3º Grupo": "0.0%",
    "4º Grupo": "100.0%",
    "Top 32": "0.0%",
    "Oitavas": "0.0%",
    "Quartas": "0.0%",
    "Semi": "0.0%",
    "Final": "0.0%",
    "Campeão": "0.0%"
  },
  {
    "Seleção": "Jordânia",
    "1º Grupo": "0.0%",
    "2º Grupo": "0.0%",
    "3º Grupo": "0.0%",
    "4º Grupo": "100.0%",
    "Top 32": "0.0%",
    "Oitavas": "0.0%",
    "Quartas": "0.0%",
    "Semi": "0.0%",
    "Final": "0.0%",
    "Campeão": "0.0%"
  },
  {
    "Seleção": "Curaçau",
    "1º Grupo": "0.0%",
    "2º Grupo": "0.0%",
    "3º Grupo": "0.0%",
    "4º Grupo": "100.0%",
    "Top 32": "0.0%",
    "Oitavas": "0.0%",
    "Quartas": "0.0%",
    "Semi": "0.0%",
    "Final": "0.0%",
    "Campeão": "0.0%"
  },
  {
    "Seleção": "Haiti",
    "1º Grupo": "0.0%",
    "2º Grupo": "0.0%",
    "3º Grupo": "0.0%",
    "4º Grupo": "100.0%",
    "Top 32": "0.0%",
    "Oitavas": "0.0%",
    "Quartas": "0.0%",
    "Semi": "0.0%",
    "Final": "0.0%",
    "Campeão": "0.0%"
  },
  {
    "Seleção": "Nova Zelândia",
    "1º Grupo": "0.0%",
    "2º Grupo": "0.0%",
    "3º Grupo": "0.0%",
    "4º Grupo": "100.0%",
    "Top 32": "0.0%",
    "Oitavas": "0.0%",
    "Quartas": "0.0%",
    "Semi": "0.0%",
    "Final": "0.0%",
    "Campeão": "0.0%"
  }
]